docscan/__init__.py
docscan/doc.py
docscan/cmd/__init__.py
docscan/cmd/cli.py
docscan/cmd/server.py
docscan-1.0.6.dist-info/LICENSE.txt
docscan-1.0.6.dist-info/METADATA
docscan-1.0.6.dist-info/WHEEL
docscan-1.0.6.dist-info/entry_points.txt
docscan-1.0.6.dist-info/top_level.txt
docscan-1.0.6.dist-info/RECORD
