Metadata-Version: 2.1
Name: docscan
Version: 1.0.6
Summary: This is a document scanner
Home-page: https://github.com/danielgatis/docscan
Author: Daniel Gatis
Author-email: danielgatis@gmail.com
License: UNKNOWN
Keywords: document,scanner,opencv
Platform: UNKNOWN
Classifier: License :: OSI Approved :: MIT License
Classifier: Programming Language :: Python :: 3 :: Only
Requires-Python: >=3.5, <4
License-File: LICENSE.txt
Requires-Dist: click
Requires-Dist: flask
Requires-Dist: imutils
Requires-Dist: numpy
Requires-Dist: opencv-python
Requires-Dist: rembg
Requires-Dist: waitress
